{
	"name": "relationship-zzutoyaxze",
	"properties": {
		"Name": "relationship-zzutoyaxze",
		"EntityType": "RELATIONSHIP",
		"Namespace": {
			"DatabaseName": "Database1"
		},
		"Origin": {
			"Type": "SPARK"
		},
		"FromTableName": "Religion",
		"ToTableName": "PartyReligion",
		"ColumnRelationshipInformations": [
			{
				"FromColumnName": "ReligionId",
				"ToColumnName": "ReligionId"
			}
		],
		"RelationshipType": 0,
		"Properties": {
			"DerivedModelRelationshipInfo": "{\"baseRelationship\":{\"fromEntity\":\"Religion.cdm.json/Religion\",\"toEntity\":\"PartyReligion.cdm.json/PartyReligion\",\"joinPairs\":[{\"fromAttribute\":\"ReligionId\",\"toAttribute\":\"ReligionId\"}]}}"
		}
	},
	"type": "RELATIONSHIP"
}