{
	"name": "relationship-zoabdpouhv",
	"properties": {
		"Name": "relationship-zoabdpouhv",
		"EntityType": "RELATIONSHIP",
		"Namespace": {
			"DatabaseName": "Database1"
		},
		"Origin": {
			"Type": "SPARK"
		},
		"FromTableName": "HousingUnitType",
		"ToTableName": "HouseholdLocation",
		"ColumnRelationshipInformations": [
			{
				"FromColumnName": "HousingUnitTypeId",
				"ToColumnName": "HousingUnitTypeId"
			}
		],
		"RelationshipType": 0,
		"Properties": {
			"DerivedModelRelationshipInfo": "{\"baseRelationship\":{\"fromEntity\":\"HousingUnitType.cdm.json/HousingUnitType\",\"toEntity\":\"HouseholdLocation.cdm.json/HouseholdLocation\",\"joinPairs\":[{\"fromAttribute\":\"HousingUnitTypeId\",\"toAttribute\":\"HousingUnitTypeId\"}]}}"
		}
	},
	"type": "RELATIONSHIP"
}