{
	"name": "relationship-lfawivkwko",
	"properties": {
		"Name": "relationship-lfawivkwko",
		"EntityType": "RELATIONSHIP",
		"Namespace": {
			"DatabaseName": "Database1"
		},
		"Origin": {
			"Type": "SPARK"
		},
		"FromTableName": "IndividualParty",
		"ToTableName": "PartyBiometric",
		"ColumnRelationshipInformations": [
			{
				"FromColumnName": "PartyId",
				"ToColumnName": "PartyId"
			}
		],
		"RelationshipType": 0,
		"Properties": {
			"DerivedModelRelationshipInfo": "{\"baseRelationship\":{\"fromEntity\":\"IndividualParty.cdm.json/IndividualParty\",\"toEntity\":\"PartyBiometric.cdm.json/PartyBiometric\",\"joinPairs\":[{\"fromAttribute\":\"PartyId\",\"toAttribute\":\"PartyId\"}]}}"
		}
	},
	"type": "RELATIONSHIP"
}