{
	"name": "relationship-gupuepewjs",
	"properties": {
		"Name": "relationship-gupuepewjs",
		"EntityType": "RELATIONSHIP",
		"Namespace": {
			"DatabaseName": "Database1"
		},
		"Origin": {
			"Type": "SPARK"
		},
		"FromTableName": "LifeInsurancePolicy",
		"ToTableName": "InsurancePolicyRelatedChannel",
		"ColumnRelationshipInformations": [
			{
				"FromColumnName": "InsurancePolicyId",
				"ToColumnName": "InsurancePolicyId"
			}
		],
		"RelationshipType": 0,
		"Properties": {
			"DerivedModelRelationshipInfo": "{\"baseRelationship\":{\"fromEntity\":\"LifeInsurancePolicy.cdm.json/LifeInsurancePolicy\",\"toEntity\":\"InsurancePolicyRelatedChannel.cdm.json/InsurancePolicyRelatedChannel\",\"joinPairs\":[{\"fromAttribute\":\"InsurancePolicyId\",\"toAttribute\":\"InsurancePolicyId\"}]}}"
		}
	},
	"type": "RELATIONSHIP"
}