{
	"name": "relationship-mytodhfucd",
	"properties": {
		"Name": "relationship-mytodhfucd",
		"EntityType": "RELATIONSHIP",
		"Namespace": {
			"DatabaseName": "Database1"
		},
		"Origin": {
			"Type": "SPARK"
		},
		"FromTableName": "NamePreference",
		"ToTableName": "PartyNamePreference",
		"ColumnRelationshipInformations": [
			{
				"FromColumnName": "NamePreferenceId",
				"ToColumnName": "NamePreferenceId"
			}
		],
		"RelationshipType": 0,
		"Properties": {
			"DerivedModelRelationshipInfo": "{\"baseRelationship\":{\"fromEntity\":\"NamePreference.cdm.json/NamePreference\",\"toEntity\":\"PartyNamePreference.cdm.json/PartyNamePreference\",\"joinPairs\":[{\"fromAttribute\":\"NamePreferenceId\",\"toAttribute\":\"NamePreferenceId\"}]}}"
		}
	},
	"type": "RELATIONSHIP"
}