{
	"name": "relationship-gensblpvnp",
	"properties": {
		"Name": "relationship-gensblpvnp",
		"EntityType": "RELATIONSHIP",
		"Namespace": {
			"DatabaseName": "Database1"
		},
		"Origin": {
			"Type": "SPARK"
		},
		"FromTableName": "NamePrefix",
		"ToTableName": "PartyNamePrefix",
		"ColumnRelationshipInformations": [
			{
				"FromColumnName": "NamePrefixId",
				"ToColumnName": "NamePrefixId"
			}
		],
		"RelationshipType": 0,
		"Properties": {
			"DerivedModelRelationshipInfo": "{\"baseRelationship\":{\"fromEntity\":\"NamePrefix.cdm.json/NamePrefix\",\"toEntity\":\"PartyNamePrefix.cdm.json/PartyNamePrefix\",\"joinPairs\":[{\"fromAttribute\":\"NamePrefixId\",\"toAttribute\":\"NamePrefixId\"}]}}"
		}
	},
	"type": "RELATIONSHIP"
}