{
	"name": "relationship-vjdvkvpdnx",
	"properties": {
		"Name": "relationship-vjdvkvpdnx",
		"EntityType": "RELATIONSHIP",
		"Namespace": {
			"DatabaseName": "Database1"
		},
		"Origin": {
			"Type": "SPARK"
		},
		"FromTableName": "Commission",
		"ToTableName": "ChannelCommission",
		"ColumnRelationshipInformations": [
			{
				"FromColumnName": "CommissionId",
				"ToColumnName": "CommissionId"
			}
		],
		"RelationshipType": 0,
		"Properties": {
			"DerivedModelRelationshipInfo": "{\"baseRelationship\":{\"fromEntity\":\"Commission.cdm.json/Commission\",\"toEntity\":\"ChannelCommission.cdm.json/ChannelCommission\",\"joinPairs\":[{\"fromAttribute\":\"CommissionId\",\"toAttribute\":\"CommissionId\"}]}}"
		}
	},
	"type": "RELATIONSHIP"
}