{
	"name": "relationship-xdlwlfkcle",
	"properties": {
		"Name": "relationship-xdlwlfkcle",
		"EntityType": "RELATIONSHIP",
		"Namespace": {
			"DatabaseName": "Database1"
		},
		"Origin": {
			"Type": "SPARK"
		},
		"FromTableName": "Household",
		"ToTableName": "RelatedHousehold",
		"ColumnRelationshipInformations": [
			{
				"FromColumnName": "HouseholdId",
				"ToColumnName": "HouseholdId"
			}
		],
		"RelationshipType": 0,
		"Properties": {
			"DerivedModelRelationshipInfo": "{\"baseRelationship\":{\"fromEntity\":\"Household.cdm.json/Household\",\"toEntity\":\"RelatedHousehold.cdm.json/RelatedHousehold\",\"joinPairs\":[{\"fromAttribute\":\"HouseholdId\",\"toAttribute\":\"HouseholdId\"}]}}"
		}
	},
	"type": "RELATIONSHIP"
}