{
	"name": "GroupMember",
	"properties": {
		"Name": "GroupMember",
		"EntityType": "TABLE",
		"Namespace": {
			"DatabaseName": "Database1"
		},
		"Description": "A member of the Sponsored Group.",
		"TableType": "EXTERNAL",
		"Origin": {
			"Type": "SPARK"
		},
		"StorageDescriptor": {
			"Columns": [
				{
					"Name": "MasterContractId",
					"Description": "The unique identifier of a Master Contract.",
					"BaseAttributeReference": {
						"Entity": "GroupMember.cdm.json/GroupMember",
						"Name": "MasterContractId"
					},
					"OriginDataTypeName": {
						"TypeName": "integer",
						"IsComplexType": false,
						"IsNullable": false,
						"Properties": {
							"HIVE_TYPE_STRING": "integer"
						}
					}
				},
				{
					"Name": "PolicyholderId",
					"Description": "The unique identifier of a Policyholder.",
					"BaseAttributeReference": {
						"Entity": "GroupMember.cdm.json/GroupMember",
						"Name": "PolicyholderId"
					},
					"OriginDataTypeName": {
						"TypeName": "integer",
						"IsComplexType": false,
						"IsNullable": false,
						"Properties": {
							"HIVE_TYPE_STRING": "integer"
						}
					}
				},
				{
					"Name": "MemberGroupStartDate",
					"Description": "The starting date of the member's Sponsor-related participation.",
					"BaseAttributeReference": {
						"Entity": "GroupMember.cdm.json/GroupMember",
						"Name": "MemberGroupStartDate"
					},
					"OriginDataTypeName": {
						"TypeName": "date",
						"IsComplexType": false,
						"IsNullable": false,
						"Properties": {
							"DateFormat": "YYYY-MM-DD",
							"HIVE_TYPE_STRING": "date"
						}
					}
				},
				{
					"Name": "MemberGroupEndDate",
					"Description": "The ending date of the member's Sponsor-related participation.",
					"BaseAttributeReference": {
						"Entity": "GroupMember.cdm.json/GroupMember",
						"Name": "MemberGroupEndDate"
					},
					"OriginDataTypeName": {
						"TypeName": "date",
						"IsComplexType": false,
						"IsNullable": true,
						"Properties": {
							"DateFormat": "YYYY-MM-DD",
							"HIVE_TYPE_STRING": "date"
						}
					}
				},
				{
					"Name": "MemberGroupEligibilityPeriod",
					"Description": "The number of years of eligibility that the member has within the Sponsored organization.",
					"BaseAttributeReference": {
						"Entity": "GroupMember.cdm.json/GroupMember",
						"Name": "MemberGroupEligibilityPeriod"
					},
					"OriginDataTypeName": {
						"TypeName": "integer",
						"IsComplexType": false,
						"IsNullable": true,
						"Properties": {
							"HIVE_TYPE_STRING": "integer"
						}
					}
				},
				{
					"Name": "EligibilityStatusId",
					"Description": "The unique identifier of an Eligibility Status.",
					"BaseAttributeReference": {
						"Entity": "GroupMember.cdm.json/GroupMember",
						"Name": "EligibilityStatusId"
					},
					"OriginDataTypeName": {
						"TypeName": "integer",
						"IsComplexType": false,
						"IsNullable": false,
						"Properties": {
							"HIVE_TYPE_STRING": "integer"
						}
					}
				}
			],
			"Properties": {
				"textinputformat.record.delimiter": ",",
				"compression": "",
				"derivedModelAttributeInfo": "{\"attributeReferences\":{\"MasterContractId\":{\"entity\":\"GroupMember.cdm.json/GroupMember\",\"name\":\"MasterContractId\"},\"PolicyholderId\":{\"entity\":\"GroupMember.cdm.json/GroupMember\",\"name\":\"PolicyholderId\"},\"MemberGroupStartDate\":{\"entity\":\"GroupMember.cdm.json/GroupMember\",\"name\":\"MemberGroupStartDate\"},\"MemberGroupEndDate\":{\"entity\":\"GroupMember.cdm.json/GroupMember\",\"name\":\"MemberGroupEndDate\"},\"MemberGroupEligibilityPeriod\":{\"entity\":\"GroupMember.cdm.json/GroupMember\",\"name\":\"MemberGroupEligibilityPeriod\"},\"EligibilityStatusId\":{\"entity\":\"GroupMember.cdm.json/GroupMember\",\"name\":\"EligibilityStatusId\"}}}"
			},
			"Compressed": false,
			"IsStoredAsSubdirectories": false
		},
		"Properties": {
			"DerivedModelEntityInfo": "{\"entityDirectives\":{\"baseEntityReference\":{\"name\":\"GroupMember\",\"path\":\"GroupMember.cdm.json/GroupMember\"},\"description\":\"A member of the Sponsored Group.\",\"primaryKey\":[\"MasterContractId\",\"PolicyholderId\",\"MemberGroupStartDate\"],\"projectionInfo\":{\"attributes\":[{\"type\":\"Existing\",\"attributeReference\":{\"entity\":\"GroupMember.cdm.json/GroupMember\",\"name\":\"MasterContractId\"},\"dataType\":\"integer\",\"description\":\"The unique identifier of a Master Contract.\",\"isNullable\":false,\"name\":\"MasterContractId\"},{\"type\":\"Existing\",\"attributeReference\":{\"entity\":\"GroupMember.cdm.json/GroupMember\",\"name\":\"PolicyholderId\"},\"dataType\":\"integer\",\"description\":\"The unique identifier of a Policyholder.\",\"isNullable\":false,\"name\":\"PolicyholderId\"},{\"type\":\"Existing\",\"attributeReference\":{\"entity\":\"GroupMember.cdm.json/GroupMember\",\"name\":\"MemberGroupStartDate\"},\"dataType\":\"date\",\"dateFormat\":\"YYYY-MM-DD\",\"description\":\"The starting date of the member's Sponsor-related participation.\",\"isNullable\":false,\"name\":\"MemberGroupStartDate\"},{\"type\":\"Existing\",\"attributeReference\":{\"entity\":\"GroupMember.cdm.json/GroupMember\",\"name\":\"MemberGroupEndDate\"},\"dataType\":\"date\",\"dateFormat\":\"YYYY-MM-DD\",\"description\":\"The ending date of the member's Sponsor-related participation.\",\"isNullable\":true,\"name\":\"MemberGroupEndDate\"},{\"type\":\"Existing\",\"attributeReference\":{\"entity\":\"GroupMember.cdm.json/GroupMember\",\"name\":\"MemberGroupEligibilityPeriod\"},\"dataType\":\"integer\",\"description\":\"The number of years of eligibility that the member has within the Sponsored organization.\",\"isNullable\":true,\"name\":\"MemberGroupEligibilityPeriod\"},{\"type\":\"Existing\",\"attributeReference\":{\"entity\":\"GroupMember.cdm.json/GroupMember\",\"name\":\"EligibilityStatusId\"},\"dataType\":\"integer\",\"description\":\"The unique identifier of an Eligibility Status.\",\"isNullable\":false,\"name\":\"EligibilityStatusId\"}]}}}",
			"Description": "A member of the Sponsored Group.",
			"DisplayFolderInfo": "{\"name\":\"Party\",\"colorCode\":\"#0E3D73\"}",
			"PrimaryKeys": "MasterContractId,PolicyholderId,MemberGroupStartDate"
		},
		"Retention": 0,
		"Temporary": false,
		"IsRewriteEnabled": false
	},
	"type": "TABLE"
}