{
	"name": "InsuranceEndorsement",
	"properties": {
		"Name": "InsuranceEndorsement",
		"EntityType": "TABLE",
		"Namespace": {
			"DatabaseName": "Database1"
		},
		"Description": "An Endorsement that may be applied to the Insurance Product.\n\nAn Endorsement is an amendment to the policy written especially to cover unique items just for you. \n\nAn endorsement is also a change to your policy that is made during the policy's term. An endorsement is attached to your policy to modify the terms of the insurance contract.",
		"TableType": "EXTERNAL",
		"Origin": {
			"Type": "SPARK"
		},
		"StorageDescriptor": {
			"Columns": [
				{
					"Name": "InsuranceEndorsementId",
					"Description": "The unique identifier of an Insurance Endorsement.",
					"BaseAttributeReference": {
						"Entity": "InsuranceEndorsement.cdm.json/InsuranceEndorsement",
						"Name": "InsuranceEndorsementId"
					},
					"OriginDataTypeName": {
						"TypeName": "integer",
						"IsComplexType": false,
						"IsNullable": false,
						"Properties": {
							"HIVE_TYPE_STRING": "integer"
						}
					}
				},
				{
					"Name": "InsuranceEndorsementTypeName",
					"Description": "The name of an Insurance Endorsement.",
					"BaseAttributeReference": {
						"Entity": "InsuranceEndorsement.cdm.json/InsuranceEndorsement",
						"Name": "InsuranceEndorsementTypeName"
					},
					"OriginDataTypeName": {
						"TypeName": "string",
						"IsComplexType": false,
						"IsNullable": true,
						"Length": 128,
						"Properties": {
							"HIVE_TYPE_STRING": "string"
						}
					}
				},
				{
					"Name": "InsuranceEndorsementTypeDescription",
					"Description": "The description of an Insurance Endorsement.",
					"BaseAttributeReference": {
						"Entity": "InsuranceEndorsement.cdm.json/InsuranceEndorsement",
						"Name": "InsuranceEndorsementTypeDescription"
					},
					"OriginDataTypeName": {
						"TypeName": "string",
						"IsComplexType": false,
						"IsNullable": true,
						"Length": 512,
						"Properties": {
							"HIVE_TYPE_STRING": "string"
						}
					}
				},
				{
					"Name": "InsuranceEndorsementStatement",
					"Description": "The text of the endorsement.",
					"BaseAttributeReference": {
						"Entity": "InsuranceEndorsement.cdm.json/InsuranceEndorsement",
						"Name": "InsuranceEndorsementStatement"
					},
					"OriginDataTypeName": {
						"TypeName": "string",
						"IsComplexType": false,
						"IsNullable": true,
						"Length": 2048,
						"Properties": {
							"HIVE_TYPE_STRING": "string"
						}
					}
				},
				{
					"Name": "InsuranceEndorsementTermsAndConditions",
					"Description": "The terms and conditions associated with the Insurance Endorsement.",
					"BaseAttributeReference": {
						"Entity": "InsuranceEndorsement.cdm.json/InsuranceEndorsement",
						"Name": "InsuranceEndorsementTermsAndConditions"
					},
					"OriginDataTypeName": {
						"TypeName": "string",
						"IsComplexType": false,
						"IsNullable": true,
						"Length": 2048,
						"Properties": {
							"HIVE_TYPE_STRING": "string"
						}
					}
				},
				{
					"Name": "InsuranceEndorsementExclusions",
					"Description": "Exclusions associated with the Insurance Endorsement.",
					"BaseAttributeReference": {
						"Entity": "InsuranceEndorsement.cdm.json/InsuranceEndorsement",
						"Name": "InsuranceEndorsementExclusions"
					},
					"OriginDataTypeName": {
						"TypeName": "string",
						"IsComplexType": false,
						"IsNullable": true,
						"Length": 2048,
						"Properties": {
							"HIVE_TYPE_STRING": "string"
						}
					}
				},
				{
					"Name": "InsuranceEndorsementTypeId",
					"Description": "The unique identifier of an Insurance Endorsement Type.",
					"BaseAttributeReference": {
						"Entity": "InsuranceEndorsement.cdm.json/InsuranceEndorsement",
						"Name": "InsuranceEndorsementTypeId"
					},
					"OriginDataTypeName": {
						"TypeName": "integer",
						"IsComplexType": false,
						"IsNullable": true,
						"Properties": {
							"HIVE_TYPE_STRING": "integer"
						}
					}
				}
			],
			"Properties": {
				"textinputformat.record.delimiter": ",",
				"compression": "",
				"derivedModelAttributeInfo": "{\"attributeReferences\":{\"InsuranceEndorsementId\":{\"entity\":\"InsuranceEndorsement.cdm.json/InsuranceEndorsement\",\"name\":\"InsuranceEndorsementId\"},\"InsuranceEndorsementTypeName\":{\"entity\":\"InsuranceEndorsement.cdm.json/InsuranceEndorsement\",\"name\":\"InsuranceEndorsementTypeName\"},\"InsuranceEndorsementTypeDescription\":{\"entity\":\"InsuranceEndorsement.cdm.json/InsuranceEndorsement\",\"name\":\"InsuranceEndorsementTypeDescription\"},\"InsuranceEndorsementStatement\":{\"entity\":\"InsuranceEndorsement.cdm.json/InsuranceEndorsement\",\"name\":\"InsuranceEndorsementStatement\"},\"InsuranceEndorsementTermsAndConditions\":{\"entity\":\"InsuranceEndorsement.cdm.json/InsuranceEndorsement\",\"name\":\"InsuranceEndorsementTermsAndConditions\"},\"InsuranceEndorsementExclusions\":{\"entity\":\"InsuranceEndorsement.cdm.json/InsuranceEndorsement\",\"name\":\"InsuranceEndorsementExclusions\"},\"InsuranceEndorsementTypeId\":{\"entity\":\"InsuranceEndorsement.cdm.json/InsuranceEndorsement\",\"name\":\"InsuranceEndorsementTypeId\"}}}"
			},
			"Compressed": false,
			"IsStoredAsSubdirectories": false
		},
		"Properties": {
			"DerivedModelEntityInfo": "{\"entityDirectives\":{\"baseEntityReference\":{\"name\":\"InsuranceEndorsement\",\"path\":\"InsuranceEndorsement.cdm.json/InsuranceEndorsement\"},\"description\":\"An Endorsement that may be applied to the Insurance Product.\\n\\nAn Endorsement is an amendment to the policy written especially to cover unique items just for you. \\n\\nAn endorsement is also a change to your policy that is made during the policy's term. An endorsement is attached to your policy to modify the terms of the insurance contract.\",\"primaryKey\":[\"InsuranceEndorsementId\"],\"projectionInfo\":{\"attributes\":[{\"type\":\"Existing\",\"attributeReference\":{\"entity\":\"InsuranceEndorsement.cdm.json/InsuranceEndorsement\",\"name\":\"InsuranceEndorsementId\"},\"dataType\":\"integer\",\"description\":\"The unique identifier of an Insurance Endorsement.\",\"isNullable\":false,\"name\":\"InsuranceEndorsementId\"},{\"type\":\"Existing\",\"attributeReference\":{\"entity\":\"InsuranceEndorsement.cdm.json/InsuranceEndorsement\",\"name\":\"InsuranceEndorsementTypeName\"},\"dataType\":\"string\",\"dataTypeLength\":128,\"description\":\"The name of an Insurance Endorsement.\",\"isNullable\":true,\"name\":\"InsuranceEndorsementTypeName\"},{\"type\":\"Existing\",\"attributeReference\":{\"entity\":\"InsuranceEndorsement.cdm.json/InsuranceEndorsement\",\"name\":\"InsuranceEndorsementTypeDescription\"},\"dataType\":\"string\",\"dataTypeLength\":512,\"description\":\"The description of an Insurance Endorsement.\",\"isNullable\":true,\"name\":\"InsuranceEndorsementTypeDescription\"},{\"type\":\"Existing\",\"attributeReference\":{\"entity\":\"InsuranceEndorsement.cdm.json/InsuranceEndorsement\",\"name\":\"InsuranceEndorsementStatement\"},\"dataType\":\"string\",\"dataTypeLength\":2048,\"description\":\"The text of the endorsement.\",\"isNullable\":true,\"name\":\"InsuranceEndorsementStatement\"},{\"type\":\"Existing\",\"attributeReference\":{\"entity\":\"InsuranceEndorsement.cdm.json/InsuranceEndorsement\",\"name\":\"InsuranceEndorsementTermsAndConditions\"},\"dataType\":\"string\",\"dataTypeLength\":2048,\"description\":\"The terms and conditions associated with the Insurance Endorsement.\",\"isNullable\":true,\"name\":\"InsuranceEndorsementTermsAndConditions\"},{\"type\":\"Existing\",\"attributeReference\":{\"entity\":\"InsuranceEndorsement.cdm.json/InsuranceEndorsement\",\"name\":\"InsuranceEndorsementExclusions\"},\"dataType\":\"string\",\"dataTypeLength\":2048,\"description\":\"Exclusions associated with the Insurance Endorsement.\",\"isNullable\":true,\"name\":\"InsuranceEndorsementExclusions\"},{\"type\":\"Existing\",\"attributeReference\":{\"entity\":\"InsuranceEndorsement.cdm.json/InsuranceEndorsement\",\"name\":\"InsuranceEndorsementTypeId\"},\"dataType\":\"integer\",\"description\":\"The unique identifier of an Insurance Endorsement Type.\",\"isNullable\":true,\"name\":\"InsuranceEndorsementTypeId\"}]}}}",
			"Description": "An Endorsement that may be applied to the Insurance Product.\n\nAn Endorsement is an amendment to the policy written especially to cover unique items just for you. \n\nAn endorsement is also a change to your policy that is made during the policy's term. An endorsement is attached to your policy to modify the terms of the insurance contract.",
			"DisplayFolderInfo": "{\"name\":\"Product\",\"colorCode\":\"#7D0F6C\"}",
			"PrimaryKeys": "InsuranceEndorsementId"
		},
		"Retention": 0,
		"Temporary": false,
		"IsRewriteEnabled": false
	},
	"type": "TABLE"
}