{
	"name": "MasterContract",
	"properties": {
		"Name": "MasterContract",
		"EntityType": "TABLE",
		"Namespace": {
			"DatabaseName": "Database1"
		},
		"Description": "In Group Insurance, the Master Contract is given to the employer or participating organization.\n\nIndividuals (Policyholders) insured under the plan receive certificates to evidence their coverage under the plan.\n\nThe basic principle of group insurance is that it provides insurance coverage for a number of people under a single master contract or master policy.\n\nIt is the group that must meet the underwriting requirements of the insurance company - not the individual members.\n\nGroup insurance is a way to provide life insurance to a large number of people under a single contract ('master contract' or 'master policy').\n\nGroup insurance is typically provided by an employer for their employees as a benefit. The employer is the applicant and the contract policyholder. The employees are group members and not parties to the contract. Each employee is given a certificate of insurance that summarizes the  coverage terms and details the  employee's rights under the  contract.",
		"TableType": "EXTERNAL",
		"Origin": {
			"Type": "SPARK"
		},
		"StorageDescriptor": {
			"Columns": [
				{
					"Name": "MasterContractId",
					"Description": "The unique identifier of a Master Contract.",
					"BaseAttributeReference": {
						"Entity": "MasterContract.cdm.json/MasterContract",
						"Name": "MasterContractId"
					},
					"OriginDataTypeName": {
						"TypeName": "integer",
						"IsComplexType": false,
						"IsNullable": false,
						"Properties": {
							"HIVE_TYPE_STRING": "integer"
						}
					}
				},
				{
					"Name": "ContractSignedDate",
					"Description": "The date that the Master Contract was signed.",
					"BaseAttributeReference": {
						"Entity": "MasterContract.cdm.json/MasterContract",
						"Name": "ContractSignedDate"
					},
					"OriginDataTypeName": {
						"TypeName": "date",
						"IsComplexType": false,
						"IsNullable": true,
						"Properties": {
							"DateFormat": "YYYY-MM-DD",
							"HIVE_TYPE_STRING": "date"
						}
					}
				},
				{
					"Name": "ContractEffectiveStartDate",
					"Description": "The date that the Master Contract goes into effect.",
					"BaseAttributeReference": {
						"Entity": "MasterContract.cdm.json/MasterContract",
						"Name": "ContractEffectiveStartDate"
					},
					"OriginDataTypeName": {
						"TypeName": "date",
						"IsComplexType": false,
						"IsNullable": true,
						"Properties": {
							"DateFormat": "YYYY-MM-DD",
							"HIVE_TYPE_STRING": "date"
						}
					}
				},
				{
					"Name": "ContractEffectiveEndDate",
					"Description": "The date that the Master Contract is terminated or expires.",
					"BaseAttributeReference": {
						"Entity": "MasterContract.cdm.json/MasterContract",
						"Name": "ContractEffectiveEndDate"
					},
					"OriginDataTypeName": {
						"TypeName": "date",
						"IsComplexType": false,
						"IsNullable": true,
						"Properties": {
							"DateFormat": "YYYY-MM-DD",
							"HIVE_TYPE_STRING": "date"
						}
					}
				},
				{
					"Name": "ContractPeriodMonths",
					"Description": "The number of months that the Master Contract is to be in effect.",
					"BaseAttributeReference": {
						"Entity": "MasterContract.cdm.json/MasterContract",
						"Name": "ContractPeriodMonths"
					},
					"OriginDataTypeName": {
						"TypeName": "integer",
						"IsComplexType": false,
						"IsNullable": true,
						"Properties": {
							"HIVE_TYPE_STRING": "integer"
						}
					}
				},
				{
					"Name": "AutomaticRenewalIndicator",
					"Description": "Indicates that the Master Contract is to be automatically renewed upon expiration.",
					"BaseAttributeReference": {
						"Entity": "MasterContract.cdm.json/MasterContract",
						"Name": "AutomaticRenewalIndicator"
					},
					"OriginDataTypeName": {
						"TypeName": "boolean",
						"IsComplexType": false,
						"IsNullable": true,
						"Properties": {
							"HIVE_TYPE_STRING": "boolean"
						}
					}
				},
				{
					"Name": "AutomaticRenewalNotificationPeriod",
					"Description": "The period in days in which the Master Contract holder is to be notified in advance that the Master Contract is due to expire.",
					"BaseAttributeReference": {
						"Entity": "MasterContract.cdm.json/MasterContract",
						"Name": "AutomaticRenewalNotificationPeriod"
					},
					"OriginDataTypeName": {
						"TypeName": "decimal",
						"IsComplexType": false,
						"IsNullable": true,
						"Precision": 3,
						"Scale": 0,
						"Properties": {
							"HIVE_TYPE_STRING": "decimal"
						}
					}
				},
				{
					"Name": "PrepaidContractIndicator",
					"Description": "Indicates that the Master Contract is prepaid by the Master Contract holder.",
					"BaseAttributeReference": {
						"Entity": "MasterContract.cdm.json/MasterContract",
						"Name": "PrepaidContractIndicator"
					},
					"OriginDataTypeName": {
						"TypeName": "boolean",
						"IsComplexType": false,
						"IsNullable": true,
						"Properties": {
							"HIVE_TYPE_STRING": "boolean"
						}
					}
				},
				{
					"Name": "AnnuallyRenewableIndicator",
					"Description": "Indicates that the Master Contract can be renewed on an annual basis.",
					"BaseAttributeReference": {
						"Entity": "MasterContract.cdm.json/MasterContract",
						"Name": "AnnuallyRenewableIndicator"
					},
					"OriginDataTypeName": {
						"TypeName": "boolean",
						"IsComplexType": false,
						"IsNullable": true,
						"Properties": {
							"HIVE_TYPE_STRING": "boolean"
						}
					}
				},
				{
					"Name": "EligibilityStatement",
					"Description": "The eligibility criteria associated with membership under the Master Contract.",
					"BaseAttributeReference": {
						"Entity": "MasterContract.cdm.json/MasterContract",
						"Name": "EligibilityStatement"
					},
					"OriginDataTypeName": {
						"TypeName": "string",
						"IsComplexType": false,
						"IsNullable": true,
						"Length": 2048,
						"Properties": {
							"HIVE_TYPE_STRING": "string"
						}
					}
				},
				{
					"Name": "ConversionToIndividualPlanIndicator",
					"Description": "Most group life insurance policies contain a conversion provision that allows individuals to convert to an individual insurance plan without evidence of insurability within a specified period of days.",
					"BaseAttributeReference": {
						"Entity": "MasterContract.cdm.json/MasterContract",
						"Name": "ConversionToIndividualPlanIndicator"
					},
					"OriginDataTypeName": {
						"TypeName": "boolean",
						"IsComplexType": false,
						"IsNullable": true,
						"Properties": {
							"HIVE_TYPE_STRING": "boolean"
						}
					}
				},
				{
					"Name": "ConversionToIndividualPlanPeriod",
					"Description": "The number of days in which the individual has to convert from the group to individual insurance plan.\n\nMost group life insurance policies contain a conversion provision that allows individuals to convert to an individual insurance plan without evidence of insurability within a specified period of days.",
					"BaseAttributeReference": {
						"Entity": "MasterContract.cdm.json/MasterContract",
						"Name": "ConversionToIndividualPlanPeriod"
					},
					"OriginDataTypeName": {
						"TypeName": "decimal",
						"IsComplexType": false,
						"IsNullable": true,
						"Precision": 3,
						"Scale": 0,
						"Properties": {
							"HIVE_TYPE_STRING": "decimal"
						}
					}
				},
				{
					"Name": "MasterContractTypeId",
					"Description": "The unique identifier of a Contract Type.",
					"BaseAttributeReference": {
						"Entity": "MasterContract.cdm.json/MasterContract",
						"Name": "MasterContractTypeId"
					},
					"OriginDataTypeName": {
						"TypeName": "integer",
						"IsComplexType": false,
						"IsNullable": true,
						"Properties": {
							"HIVE_TYPE_STRING": "integer"
						}
					}
				},
				{
					"Name": "SponsorId",
					"Description": "The unique identifier of the Sponsor.",
					"BaseAttributeReference": {
						"Entity": "MasterContract.cdm.json/MasterContract",
						"Name": "SponsorId"
					},
					"OriginDataTypeName": {
						"TypeName": "integer",
						"IsComplexType": false,
						"IsNullable": false,
						"Properties": {
							"HIVE_TYPE_STRING": "integer"
						}
					}
				}
			],
			"Properties": {
				"textinputformat.record.delimiter": ",",
				"compression": "",
				"derivedModelAttributeInfo": "{\"attributeReferences\":{\"MasterContractId\":{\"entity\":\"MasterContract.cdm.json/MasterContract\",\"name\":\"MasterContractId\"},\"ContractSignedDate\":{\"entity\":\"MasterContract.cdm.json/MasterContract\",\"name\":\"ContractSignedDate\"},\"ContractEffectiveStartDate\":{\"entity\":\"MasterContract.cdm.json/MasterContract\",\"name\":\"ContractEffectiveStartDate\"},\"ContractEffectiveEndDate\":{\"entity\":\"MasterContract.cdm.json/MasterContract\",\"name\":\"ContractEffectiveEndDate\"},\"ContractPeriodMonths\":{\"entity\":\"MasterContract.cdm.json/MasterContract\",\"name\":\"ContractPeriodMonths\"},\"AutomaticRenewalIndicator\":{\"entity\":\"MasterContract.cdm.json/MasterContract\",\"name\":\"AutomaticRenewalIndicator\"},\"AutomaticRenewalNotificationPeriod\":{\"entity\":\"MasterContract.cdm.json/MasterContract\",\"name\":\"AutomaticRenewalNotificationPeriod\"},\"PrepaidContractIndicator\":{\"entity\":\"MasterContract.cdm.json/MasterContract\",\"name\":\"PrepaidContractIndicator\"},\"AnnuallyRenewableIndicator\":{\"entity\":\"MasterContract.cdm.json/MasterContract\",\"name\":\"AnnuallyRenewableIndicator\"},\"EligibilityStatement\":{\"entity\":\"MasterContract.cdm.json/MasterContract\",\"name\":\"EligibilityStatement\"},\"ConversionToIndividualPlanIndicator\":{\"entity\":\"MasterContract.cdm.json/MasterContract\",\"name\":\"ConversionToIndividualPlanIndicator\"},\"ConversionToIndividualPlanPeriod\":{\"entity\":\"MasterContract.cdm.json/MasterContract\",\"name\":\"ConversionToIndividualPlanPeriod\"},\"MasterContractTypeId\":{\"entity\":\"MasterContract.cdm.json/MasterContract\",\"name\":\"MasterContractTypeId\"},\"SponsorId\":{\"entity\":\"MasterContract.cdm.json/MasterContract\",\"name\":\"SponsorId\"}}}"
			},
			"Compressed": false,
			"IsStoredAsSubdirectories": false
		},
		"Properties": {
			"DerivedModelEntityInfo": "{\"entityDirectives\":{\"baseEntityReference\":{\"name\":\"MasterContract\",\"path\":\"MasterContract.cdm.json/MasterContract\"},\"description\":\"In Group Insurance, the Master Contract is given to the employer or participating organization.\\n\\nIndividuals (Policyholders) insured under the plan receive certificates to evidence their coverage under the plan.\\n\\nThe basic principle of group insurance is that it provides insurance coverage for a number of people under a single master contract or master policy.\\n\\nIt is the group that must meet the underwriting requirements of the insurance company - not the individual members.\\n\\nGroup insurance is a way to provide life insurance to a large number of people under a single contract ('master contract' or 'master policy').\\n\\nGroup insurance is typically provided by an employer for their employees as a benefit. The employer is the applicant and the contract policyholder. The employees are group members and not parties to the contract. Each employee is given a certificate of insurance that summarizes the  coverage terms and details the  employee's rights under the  contract.\",\"primaryKey\":[\"MasterContractId\"],\"projectionInfo\":{\"attributes\":[{\"type\":\"Existing\",\"attributeReference\":{\"entity\":\"MasterContract.cdm.json/MasterContract\",\"name\":\"MasterContractId\"},\"dataType\":\"integer\",\"description\":\"The unique identifier of a Master Contract.\",\"isNullable\":false,\"name\":\"MasterContractId\"},{\"type\":\"Existing\",\"attributeReference\":{\"entity\":\"MasterContract.cdm.json/MasterContract\",\"name\":\"ContractSignedDate\"},\"dataType\":\"date\",\"dateFormat\":\"YYYY-MM-DD\",\"description\":\"The date that the Master Contract was signed.\",\"isNullable\":true,\"name\":\"ContractSignedDate\"},{\"type\":\"Existing\",\"attributeReference\":{\"entity\":\"MasterContract.cdm.json/MasterContract\",\"name\":\"ContractEffectiveStartDate\"},\"dataType\":\"date\",\"dateFormat\":\"YYYY-MM-DD\",\"description\":\"The date that the Master Contract goes into effect.\",\"isNullable\":true,\"name\":\"ContractEffectiveStartDate\"},{\"type\":\"Existing\",\"attributeReference\":{\"entity\":\"MasterContract.cdm.json/MasterContract\",\"name\":\"ContractEffectiveEndDate\"},\"dataType\":\"date\",\"dateFormat\":\"YYYY-MM-DD\",\"description\":\"The date that the Master Contract is terminated or expires.\",\"isNullable\":true,\"name\":\"ContractEffectiveEndDate\"},{\"type\":\"Existing\",\"attributeReference\":{\"entity\":\"MasterContract.cdm.json/MasterContract\",\"name\":\"ContractPeriodMonths\"},\"dataType\":\"integer\",\"description\":\"The number of months that the Master Contract is to be in effect.\",\"isNullable\":true,\"name\":\"ContractPeriodMonths\"},{\"type\":\"Existing\",\"attributeReference\":{\"entity\":\"MasterContract.cdm.json/MasterContract\",\"name\":\"AutomaticRenewalIndicator\"},\"dataType\":\"boolean\",\"description\":\"Indicates that the Master Contract is to be automatically renewed upon expiration.\",\"isNullable\":true,\"name\":\"AutomaticRenewalIndicator\"},{\"type\":\"Existing\",\"attributeReference\":{\"entity\":\"MasterContract.cdm.json/MasterContract\",\"name\":\"AutomaticRenewalNotificationPeriod\"},\"dataType\":\"decimal\",\"dataTypeLength\":3,\"description\":\"The period in days in which the Master Contract holder is to be notified in advance that the Master Contract is due to expire.\",\"isNullable\":true,\"scale\":0,\"name\":\"AutomaticRenewalNotificationPeriod\"},{\"type\":\"Existing\",\"attributeReference\":{\"entity\":\"MasterContract.cdm.json/MasterContract\",\"name\":\"PrepaidContractIndicator\"},\"dataType\":\"boolean\",\"description\":\"Indicates that the Master Contract is prepaid by the Master Contract holder.\",\"isNullable\":true,\"name\":\"PrepaidContractIndicator\"},{\"type\":\"Existing\",\"attributeReference\":{\"entity\":\"MasterContract.cdm.json/MasterContract\",\"name\":\"AnnuallyRenewableIndicator\"},\"dataType\":\"boolean\",\"description\":\"Indicates that the Master Contract can be renewed on an annual basis.\",\"isNullable\":true,\"name\":\"AnnuallyRenewableIndicator\"},{\"type\":\"Existing\",\"attributeReference\":{\"entity\":\"MasterContract.cdm.json/MasterContract\",\"name\":\"EligibilityStatement\"},\"dataType\":\"string\",\"dataTypeLength\":2048,\"description\":\"The eligibility criteria associated with membership under the Master Contract.\",\"isNullable\":true,\"name\":\"EligibilityStatement\"},{\"type\":\"Existing\",\"attributeReference\":{\"entity\":\"MasterContract.cdm.json/MasterContract\",\"name\":\"ConversionToIndividualPlanIndicator\"},\"dataType\":\"boolean\",\"description\":\"Most group life insurance policies contain a conversion provision that allows individuals to convert to an individual insurance plan without evidence of insurability within a specified period of days.\",\"isNullable\":true,\"name\":\"ConversionToIndividualPlanIndicator\"},{\"type\":\"Existing\",\"attributeReference\":{\"entity\":\"MasterContract.cdm.json/MasterContract\",\"name\":\"ConversionToIndividualPlanPeriod\"},\"dataType\":\"decimal\",\"dataTypeLength\":3,\"description\":\"The number of days in which the individual has to convert from the group to individual insurance plan.\\n\\nMost group life insurance policies contain a conversion provision that allows individuals to convert to an individual insurance plan without evidence of insurability within a specified period of days.\",\"isNullable\":true,\"scale\":0,\"name\":\"ConversionToIndividualPlanPeriod\"},{\"type\":\"Existing\",\"attributeReference\":{\"entity\":\"MasterContract.cdm.json/MasterContract\",\"name\":\"MasterContractTypeId\"},\"dataType\":\"integer\",\"description\":\"The unique identifier of a Contract Type.\",\"isNullable\":true,\"name\":\"MasterContractTypeId\"},{\"type\":\"Existing\",\"attributeReference\":{\"entity\":\"MasterContract.cdm.json/MasterContract\",\"name\":\"SponsorId\"},\"dataType\":\"integer\",\"description\":\"The unique identifier of the Sponsor.\",\"isNullable\":false,\"name\":\"SponsorId\"}]}}}",
			"Description": "In Group Insurance, the Master Contract is given to the employer or participating organization.\n\nIndividuals (Policyholders) insured under the plan receive certificates to evidence their coverage under the plan.\n\nThe basic principle of group insurance is that it provides insurance coverage for a number of people under a single master contract or master policy.\n\nIt is the group that must meet the underwriting requirements of the insurance company - not the individual members.\n\nGroup insurance is a way to provide life insurance to a large number of people under a single contract ('master contract' or 'master policy').\n\nGroup insurance is typically provided by an employer for their employees as a benefit. The employer is the applicant and the contract policyholder. The employees are group members and not parties to the contract. Each employee is given a certificate of insurance that summarizes the  coverage terms and details the  employee's rights under the  contract.",
			"DisplayFolderInfo": "{\"name\":\"Contract\",\"colorCode\":\"#4B003F\"}",
			"PrimaryKeys": "MasterContractId"
		},
		"Retention": 0,
		"Temporary": false,
		"IsRewriteEnabled": false
	},
	"type": "TABLE"
}