{
	"name": "PartyEmail",
	"properties": {
		"Name": "PartyEmail",
		"EntityType": "TABLE",
		"Namespace": {
			"DatabaseName": "Database1"
		},
		"Description": "The party email address(s) of the associated email type for the indicated period.",
		"TableType": "EXTERNAL",
		"Origin": {
			"Type": "SPARK"
		},
		"StorageDescriptor": {
			"Columns": [
				{
					"Name": "PartyId",
					"Description": "The unique identifier of a Party.",
					"BaseAttributeReference": {
						"Entity": "PartyEmail.cdm.json/PartyEmail",
						"Name": "PartyId"
					},
					"OriginDataTypeName": {
						"TypeName": "long",
						"IsComplexType": false,
						"IsNullable": false,
						"Properties": {
							"HIVE_TYPE_STRING": "long"
						}
					}
				},
				{
					"Name": "EmailTypeId",
					"Description": "The unique identifier of an Email Type.",
					"BaseAttributeReference": {
						"Entity": "PartyEmail.cdm.json/PartyEmail",
						"Name": "EmailTypeId"
					},
					"OriginDataTypeName": {
						"TypeName": "integer",
						"IsComplexType": false,
						"IsNullable": false,
						"Properties": {
							"HIVE_TYPE_STRING": "integer"
						}
					}
				},
				{
					"Name": "EmailAddress",
					"Description": "The Party email address.",
					"BaseAttributeReference": {
						"Entity": "PartyEmail.cdm.json/PartyEmail",
						"Name": "EmailAddress"
					},
					"OriginDataTypeName": {
						"TypeName": "string",
						"IsComplexType": false,
						"IsNullable": false,
						"Length": 256,
						"Properties": {
							"HIVE_TYPE_STRING": "string"
						}
					}
				},
				{
					"Name": "PeriodStartTimestamp",
					"Description": "The period start timestamp that the information is valid or effective as of.",
					"BaseAttributeReference": {
						"Entity": "PartyEmail.cdm.json/PartyEmail",
						"Name": "PeriodStartTimestamp"
					},
					"OriginDataTypeName": {
						"TypeName": "timestamp",
						"IsComplexType": false,
						"IsNullable": false,
						"Properties": {
							"TimestampFormat": "YYYY-MM-DD HH:MM:SS.fffffffff",
							"HIVE_TYPE_STRING": "timestamp"
						}
					}
				},
				{
					"Name": "PeriodEndTimestamp",
					"Description": "The period end timestamp that the information is valid or effective as of.",
					"BaseAttributeReference": {
						"Entity": "PartyEmail.cdm.json/PartyEmail",
						"Name": "PeriodEndTimestamp"
					},
					"OriginDataTypeName": {
						"TypeName": "timestamp",
						"IsComplexType": false,
						"IsNullable": true,
						"Properties": {
							"TimestampFormat": "YYYY-MM-DD HH:MM:SS.fffffffff",
							"HIVE_TYPE_STRING": "timestamp"
						}
					}
				},
				{
					"Name": "PreferenceId",
					"Description": "The unique identifier of a Preference.",
					"BaseAttributeReference": {
						"Entity": "PartyEmail.cdm.json/PartyEmail",
						"Name": "PreferenceId"
					},
					"OriginDataTypeName": {
						"TypeName": "integer",
						"IsComplexType": false,
						"IsNullable": true,
						"Properties": {
							"HIVE_TYPE_STRING": "integer"
						}
					}
				},
				{
					"Name": "PartyEmailNote",
					"Description": "A note, comment or additional information regarding the party email address.",
					"BaseAttributeReference": {
						"Entity": "PartyEmail.cdm.json/PartyEmail",
						"Name": "PartyEmailNote"
					},
					"OriginDataTypeName": {
						"TypeName": "string",
						"IsComplexType": false,
						"IsNullable": true,
						"Length": 1024,
						"Properties": {
							"HIVE_TYPE_STRING": "string"
						}
					}
				}
			],
			"Properties": {
				"textinputformat.record.delimiter": ",",
				"compression": "",
				"derivedModelAttributeInfo": "{\"attributeReferences\":{\"PartyId\":{\"entity\":\"PartyEmail.cdm.json/PartyEmail\",\"name\":\"PartyId\"},\"EmailTypeId\":{\"entity\":\"PartyEmail.cdm.json/PartyEmail\",\"name\":\"EmailTypeId\"},\"EmailAddress\":{\"entity\":\"PartyEmail.cdm.json/PartyEmail\",\"name\":\"EmailAddress\"},\"PeriodStartTimestamp\":{\"entity\":\"PartyEmail.cdm.json/PartyEmail\",\"name\":\"PeriodStartTimestamp\"},\"PeriodEndTimestamp\":{\"entity\":\"PartyEmail.cdm.json/PartyEmail\",\"name\":\"PeriodEndTimestamp\"},\"PreferenceId\":{\"entity\":\"PartyEmail.cdm.json/PartyEmail\",\"name\":\"PreferenceId\"},\"PartyEmailNote\":{\"entity\":\"PartyEmail.cdm.json/PartyEmail\",\"name\":\"PartyEmailNote\"}}}"
			},
			"Compressed": false,
			"IsStoredAsSubdirectories": false
		},
		"Properties": {
			"DerivedModelEntityInfo": "{\"entityDirectives\":{\"baseEntityReference\":{\"name\":\"PartyEmail\",\"path\":\"PartyEmail.cdm.json/PartyEmail\"},\"description\":\"The party email address(s) of the associated email type for the indicated period.\",\"primaryKey\":[\"PartyId\",\"EmailTypeId\",\"EmailAddress\",\"PeriodStartTimestamp\"],\"projectionInfo\":{\"attributes\":[{\"type\":\"Existing\",\"attributeReference\":{\"entity\":\"PartyEmail.cdm.json/PartyEmail\",\"name\":\"PartyId\"},\"dataType\":\"long\",\"description\":\"The unique identifier of a Party.\",\"isNullable\":false,\"name\":\"PartyId\"},{\"type\":\"Existing\",\"attributeReference\":{\"entity\":\"PartyEmail.cdm.json/PartyEmail\",\"name\":\"EmailTypeId\"},\"dataType\":\"integer\",\"description\":\"The unique identifier of an Email Type.\",\"isNullable\":false,\"name\":\"EmailTypeId\"},{\"type\":\"Existing\",\"attributeReference\":{\"entity\":\"PartyEmail.cdm.json/PartyEmail\",\"name\":\"EmailAddress\"},\"dataType\":\"string\",\"dataTypeLength\":256,\"description\":\"The Party email address.\",\"isNullable\":false,\"name\":\"EmailAddress\"},{\"type\":\"Existing\",\"attributeReference\":{\"entity\":\"PartyEmail.cdm.json/PartyEmail\",\"name\":\"PeriodStartTimestamp\"},\"dataType\":\"timestamp\",\"description\":\"The period start timestamp that the information is valid or effective as of.\",\"isNullable\":false,\"name\":\"PeriodStartTimestamp\",\"timestampFormat\":\"YYYY-MM-DD HH:MM:SS.fffffffff\"},{\"type\":\"Existing\",\"attributeReference\":{\"entity\":\"PartyEmail.cdm.json/PartyEmail\",\"name\":\"PeriodEndTimestamp\"},\"dataType\":\"timestamp\",\"description\":\"The period end timestamp that the information is valid or effective as of.\",\"isNullable\":true,\"name\":\"PeriodEndTimestamp\",\"timestampFormat\":\"YYYY-MM-DD HH:MM:SS.fffffffff\"},{\"type\":\"Existing\",\"attributeReference\":{\"entity\":\"PartyEmail.cdm.json/PartyEmail\",\"name\":\"PreferenceId\"},\"dataType\":\"integer\",\"description\":\"The unique identifier of a Preference.\",\"isNullable\":true,\"name\":\"PreferenceId\"},{\"type\":\"Existing\",\"attributeReference\":{\"entity\":\"PartyEmail.cdm.json/PartyEmail\",\"name\":\"PartyEmailNote\"},\"dataType\":\"string\",\"dataTypeLength\":1024,\"description\":\"A note, comment or additional information regarding the party email address.\",\"isNullable\":true,\"name\":\"PartyEmailNote\"}]}}}",
			"Description": "The party email address(s) of the associated email type for the indicated period.",
			"DisplayFolderInfo": "{\"name\":\"Party\",\"colorCode\":\"#0E3D73\"}",
			"PrimaryKeys": "PartyId,EmailTypeId,EmailAddress,PeriodStartTimestamp"
		},
		"Retention": 0,
		"Temporary": false,
		"IsRewriteEnabled": false
	},
	"type": "TABLE"
}