{
	"name": "relationship-mijqmxsxqa",
	"properties": {
		"Name": "relationship-mijqmxsxqa",
		"EntityType": "RELATIONSHIP",
		"Namespace": {
			"DatabaseName": "Banking_wex"
		},
		"Origin": {
			"Type": "SPARK"
		},
		"FromTableName": "StoreGroupRelationshipType",
		"ToTableName": "RelatedStoreGroup",
		"ColumnRelationshipInformations": [
			{
				"FromColumnName": "StoreGroupRelationshipTypeId",
				"ToColumnName": "StoreGroupRelationshipTypeId"
			}
		],
		"RelationshipType": 0,
		"Properties": {
			"DerivedModelRelationshipInfo": "{\"baseRelationship\":{\"fromEntity\":\"StoreGroupRelationshipType.cdm.json/StoreGroupRelationshipType\",\"toEntity\":\"RelatedStoreGroup.cdm.json/RelatedStoreGroup\",\"joinPairs\":[{\"fromAttribute\":\"StoreGroupRelationshipTypeId\",\"toAttribute\":\"StoreGroupRelationshipTypeId\"}]}}"
		}
	},
	"type": "RELATIONSHIP"
}