{
	"name": "relationship-dglhaabamb",
	"properties": {
		"Name": "relationship-dglhaabamb",
		"EntityType": "RELATIONSHIP",
		"Namespace": {
			"DatabaseName": "Banking_wex"
		},
		"Origin": {
			"Type": "SPARK"
		},
		"FromTableName": "LegalEntityCustomer",
		"ToTableName": "CustomerOrganization",
		"ColumnRelationshipInformations": [
			{
				"FromColumnName": "CustomerId",
				"ToColumnName": "CustomerId"
			}
		],
		"RelationshipType": 0,
		"Properties": {
			"DerivedModelRelationshipInfo": "{\"baseRelationship\":{\"fromEntity\":\"LegalEntityCustomer.cdm.json/LegalEntityCustomer\",\"toEntity\":\"CustomerOrganization.cdm.json/CustomerOrganization\",\"joinPairs\":[{\"fromAttribute\":\"CustomerId\",\"toAttribute\":\"CustomerId\"}]}}"
		}
	},
	"type": "RELATIONSHIP"
}