{
	"name": "relationship-svbplwtbbm",
	"properties": {
		"Name": "relationship-svbplwtbbm",
		"EntityType": "RELATIONSHIP",
		"Namespace": {
			"DatabaseName": "Banking_wex"
		},
		"Origin": {
			"Type": "SPARK"
		},
		"FromTableName": "PropensityRating",
		"ToTableName": "CustomerPropensity",
		"ColumnRelationshipInformations": [
			{
				"FromColumnName": "PropensityRatingId",
				"ToColumnName": "PropensityRatingId"
			}
		],
		"RelationshipType": 0,
		"Properties": {
			"DerivedModelRelationshipInfo": "{\"baseRelationship\":{\"fromEntity\":\"PropensityRating.cdm.json/PropensityRating\",\"toEntity\":\"CustomerPropensity.cdm.json/CustomerPropensity\",\"joinPairs\":[{\"fromAttribute\":\"PropensityRatingId\",\"toAttribute\":\"PropensityRatingId\"}]}}"
		}
	},
	"type": "RELATIONSHIP"
}