{
	"name": "relationship-qddvjvyaqu",
	"properties": {
		"Name": "relationship-qddvjvyaqu",
		"EntityType": "RELATIONSHIP",
		"Namespace": {
			"DatabaseName": "Banking_wex"
		},
		"Origin": {
			"Type": "SPARK"
		},
		"FromTableName": "Contract",
		"ToTableName": "SalesRepresentativeAgreement",
		"ColumnRelationshipInformations": [
			{
				"FromColumnName": "ContractId",
				"ToColumnName": "ContractId"
			}
		],
		"RelationshipType": 0,
		"Properties": {
			"DerivedModelRelationshipInfo": "{\"baseRelationship\":{\"fromEntity\":\"Contract.cdm.json/Contract\",\"toEntity\":\"SalesRepresentativeAgreement.cdm.json/SalesRepresentativeAgreement\",\"joinPairs\":[{\"fromAttribute\":\"ContractId\",\"toAttribute\":\"ContractId\"}]}}"
		}
	},
	"type": "RELATIONSHIP"
}