{
	"name": "relationship-vawdbxmdiv",
	"properties": {
		"Name": "relationship-vawdbxmdiv",
		"EntityType": "RELATIONSHIP",
		"Namespace": {
			"DatabaseName": "Banking_wex"
		},
		"Origin": {
			"Type": "SPARK"
		},
		"FromTableName": "CommissionScheduleDetailByUnits",
		"ToTableName": "Commission",
		"ColumnRelationshipInformations": [
			{
				"FromColumnName": "CommissionMaximumNumberUnits",
				"ToColumnName": "CommissionMaximumNumberUnits"
			}
		],
		"RelationshipType": 0,
		"Properties": {
			"DerivedModelRelationshipInfo": "{\"baseRelationship\":{\"fromEntity\":\"CommissionScheduleDetailByUnits.cdm.json/CommissionScheduleDetailByUnits\",\"toEntity\":\"Commission.cdm.json/Commission\",\"joinPairs\":[{\"fromAttribute\":\"CommissionMaximumNumberUnits\",\"toAttribute\":\"CommissionMaximumNumberUnits\"}]}}"
		}
	},
	"type": "RELATIONSHIP"
}