{
	"name": "relationship-uvrmncmuwo",
	"properties": {
		"Name": "relationship-uvrmncmuwo",
		"EntityType": "RELATIONSHIP",
		"Namespace": {
			"DatabaseName": "Banking_wex"
		},
		"Origin": {
			"Type": "SPARK"
		},
		"FromTableName": "Store",
		"ToTableName": "StoreTrafficCount",
		"ColumnRelationshipInformations": [
			{
				"FromColumnName": "StoreId",
				"ToColumnName": "StoreId"
			}
		],
		"RelationshipType": 0,
		"Properties": {
			"DerivedModelRelationshipInfo": "{\"baseRelationship\":{\"fromEntity\":\"Store.cdm.json/Store\",\"toEntity\":\"StoreTrafficCount.cdm.json/StoreTrafficCount\",\"joinPairs\":[{\"fromAttribute\":\"StoreId\",\"toAttribute\":\"StoreId\"}]}}"
		}
	},
	"type": "RELATIONSHIP"
}