{
	"name": "relationship-liblaudtvv",
	"properties": {
		"Name": "relationship-liblaudtvv",
		"EntityType": "RELATIONSHIP",
		"Namespace": {
			"DatabaseName": "Banking_wex"
		},
		"Origin": {
			"Type": "SPARK"
		},
		"FromTableName": "VisitType",
		"ToTableName": "Visit",
		"ColumnRelationshipInformations": [
			{
				"FromColumnName": "VisitTypeId",
				"ToColumnName": "VisitTypeId"
			}
		],
		"RelationshipType": 0,
		"Properties": {
			"DerivedModelRelationshipInfo": "{\"baseRelationship\":{\"fromEntity\":\"VisitType.cdm.json/VisitType\",\"toEntity\":\"Visit.cdm.json/Visit\",\"joinPairs\":[{\"fromAttribute\":\"VisitTypeId\",\"toAttribute\":\"VisitTypeId\"}]}}"
		}
	},
	"type": "RELATIONSHIP"
}