{
	"name": "relationship-byqiolwjsd",
	"properties": {
		"Name": "relationship-byqiolwjsd",
		"EntityType": "RELATIONSHIP",
		"Namespace": {
			"DatabaseName": "Banking_wex"
		},
		"Origin": {
			"Type": "SPARK"
		},
		"FromTableName": "StoreFloor",
		"ToTableName": "StoreDisplayArea",
		"ColumnRelationshipInformations": [
			{
				"FromColumnName": "StoreId",
				"ToColumnName": "StoreId"
			}
		],
		"RelationshipType": 0,
		"Properties": {
			"DerivedModelRelationshipInfo": "{\"baseRelationship\":{\"fromEntity\":\"StoreFloor.cdm.json/StoreFloor\",\"toEntity\":\"StoreDisplayArea.cdm.json/StoreDisplayArea\",\"joinPairs\":[{\"fromAttribute\":\"StoreId\",\"toAttribute\":\"StoreId\"}]}}"
		}
	},
	"type": "RELATIONSHIP"
}