{
	"name": "relationship-nurymiloid",
	"properties": {
		"Name": "relationship-nurymiloid",
		"EntityType": "RELATIONSHIP",
		"Namespace": {
			"DatabaseName": "Banking_wex"
		},
		"Origin": {
			"Type": "SPARK"
		},
		"FromTableName": "SourceDocument",
		"ToTableName": "JournalTransaction",
		"ColumnRelationshipInformations": [
			{
				"FromColumnName": "SourceDocumentId",
				"ToColumnName": "SourceDocumentId"
			}
		],
		"RelationshipType": 0,
		"Properties": {
			"DerivedModelRelationshipInfo": "{\"baseRelationship\":{\"fromEntity\":\"SourceDocument.cdm.json/SourceDocument\",\"toEntity\":\"JournalTransaction.cdm.json/JournalTransaction\",\"joinPairs\":[{\"fromAttribute\":\"SourceDocumentId\",\"toAttribute\":\"SourceDocumentId\"}]}}"
		}
	},
	"type": "RELATIONSHIP"
}