{
	"name": "relationship-wbyibinylp",
	"properties": {
		"Name": "relationship-wbyibinylp",
		"EntityType": "RELATIONSHIP",
		"Namespace": {
			"DatabaseName": "Banking_wex"
		},
		"Origin": {
			"Type": "SPARK"
		},
		"FromTableName": "LegalEntityCustomer",
		"ToTableName": "CustomerTradeName",
		"ColumnRelationshipInformations": [
			{
				"FromColumnName": "CustomerId",
				"ToColumnName": "CustomerId"
			}
		],
		"RelationshipType": 0,
		"Properties": {
			"DerivedModelRelationshipInfo": "{\"baseRelationship\":{\"fromEntity\":\"LegalEntityCustomer.cdm.json/LegalEntityCustomer\",\"toEntity\":\"CustomerTradeName.cdm.json/CustomerTradeName\",\"joinPairs\":[{\"fromAttribute\":\"CustomerId\",\"toAttribute\":\"CustomerId\"}]}}"
		}
	},
	"type": "RELATIONSHIP"
}