{
	"name": "relationship-gidgmjhoeo",
	"properties": {
		"Name": "relationship-gidgmjhoeo",
		"EntityType": "RELATIONSHIP",
		"Namespace": {
			"DatabaseName": "Banking_wex"
		},
		"Origin": {
			"Type": "SPARK"
		},
		"FromTableName": "BankingProduct",
		"ToTableName": "StoreProductAvailability",
		"ColumnRelationshipInformations": [
			{
				"FromColumnName": "ProductId",
				"ToColumnName": "ProductId"
			}
		],
		"RelationshipType": 0,
		"Properties": {
			"DerivedModelRelationshipInfo": "{\"baseRelationship\":{\"fromEntity\":\"BankingProduct.cdm.json/BankingProduct\",\"toEntity\":\"StoreProductAvailability.cdm.json/StoreProductAvailability\",\"joinPairs\":[{\"fromAttribute\":\"ProductId\",\"toAttribute\":\"ProductId\"}]}}"
		}
	},
	"type": "RELATIONSHIP"
}