{
	"name": "relationship-aiqjnwqucz",
	"properties": {
		"Name": "relationship-aiqjnwqucz",
		"EntityType": "RELATIONSHIP",
		"Namespace": {
			"DatabaseName": "Banking_wex"
		},
		"Origin": {
			"Type": "SPARK"
		},
		"FromTableName": "Carrier",
		"ToTableName": "Order",
		"ColumnRelationshipInformations": [
			{
				"FromColumnName": "CarrierId",
				"ToColumnName": "CarrierId"
			}
		],
		"RelationshipType": 0,
		"Properties": {
			"DerivedModelRelationshipInfo": "{\"baseRelationship\":{\"fromEntity\":\"Carrier.cdm.json/Carrier\",\"toEntity\":\"Order.cdm.json/Order\",\"joinPairs\":[{\"fromAttribute\":\"CarrierId\",\"toAttribute\":\"CarrierId\"}]}}"
		}
	},
	"type": "RELATIONSHIP"
}